wzhmultimap.py
wzhmultimap-0.0.7.dist-info/METADATA
wzhmultimap-0.0.7.dist-info/WHEEL
wzhmultimap-0.0.7.dist-info/licenses/LICENSE
wzhmultimap-0.0.7.dist-info/RECORD
